[ {
  "numeroOrdem" : null,
  "cliente" : {
    "nome" : "João Silva",
    "telefone" : "",
    "endereco" : "",
    "clienteId" : "CLI0011",
    "veiculos" : [ ],
    "cpfAnonimizado" : ""
  },
  "veiculo" : null,
  "servicos" : [ {
    "nome" : "Troca de óleo",
    "descricao" : "Troca de óleo e filtro",
    "valor" : 150.0,
    "tempoEstimado" : 60,
    "requerElevador" : false
  } ],
  "responsavel" : {
    "nome" : "José Mecânico",
    "telefone" : "",
    "endereco" : "",
    "cargo" : "Mecânico",
    "salario" : 0.0,
    "matricula" : "TEMP",
    "departamento" : "Temporário",
    "especialidades" : [ ],
    "isEspecialista" : false,
    "especialista" : false
  },
  "data" : "01/05/2024",
  "horario" : "09:00",
  "status" : "Concluído",
  "elevadorAlocado" : null,
  "itensUtilizados" : [ {
    "codigo" : "P001",
    "nome" : "Óleo Motor",
    "quantidade" : 50,
    "preco" : 35.0,
    "descricao" : "Óleo sintético 5W30"
  } ],
  "tipo" : "Entrada",
  "categoria" : "Serviços",
  "descricao" : "Servicos e peças",
  "valor" : 1900.0,
  "problemaDetectado" : null,
  "especialidadeNecessaria" : null,
  "inspetor" : null,
  "avaliacao" : 0.0,
  "pago" : false,
  "formaPagamento" : null,
  "id" : null
}, {
  "numeroOrdem" : "41bcc418",
  "cliente" : null,
  "veiculo" : null,
  "servicos" : [ ],
  "responsavel" : null,
  "data" : "01/05/2024",
  "horario" : "14:34",
  "status" : "Pendente",
  "elevadorAlocado" : null,
  "itensUtilizados" : [ {
    "codigo" : "P001",
    "nome" : "Óleo Motor",
    "quantidade" : 50,
    "preco" : 35.0,
    "descricao" : "Óleo sintético 5W30"
  } ],
  "tipo" : "Saída",
  "categoria" : "Despesa",
  "descricao" : "Compra de peças para ordem de serviço",
  "valor" : 1750.0,
  "problemaDetectado" : null,
  "especialidadeNecessaria" : null,
  "inspetor" : null,
  "avaliacao" : 0.0,
  "pago" : false,
  "formaPagamento" : null,
  "id" : null
}, {
  "numeroOrdem" : null,
  "cliente" : {
    "nome" : "Maria Santos",
    "telefone" : "",
    "endereco" : "",
    "clienteId" : "CLI0012",
    "veiculos" : [ ],
    "cpfAnonimizado" : ""
  },
  "veiculo" : null,
  "servicos" : [ {
    "nome" : "Alinhamento",
    "descricao" : "Alinhamento e balanceamento",
    "valor" : 200.0,
    "tempoEstimado" : 90,
    "requerElevador" : false
  } ],
  "responsavel" : {
    "nome" : "Antonio Elétrico",
    "telefone" : "",
    "endereco" : "",
    "cargo" : "Mecânico",
    "salario" : 0.0,
    "matricula" : "TEMP",
    "departamento" : "Temporário",
    "especialidades" : [ ],
    "isEspecialista" : false,
    "especialista" : false
  },
  "data" : "02/05/2024",
  "horario" : "10:00",
  "status" : "Concluído",
  "elevadorAlocado" : null,
  "itensUtilizados" : [ {
    "codigo" : "P002",
    "nome" : "Filtro de Óleo",
    "quantidade" : 30,
    "preco" : 25.0,
    "descricao" : "Filtro de óleo"
  } ],
  "tipo" : "Entrada",
  "categoria" : "Serviços",
  "descricao" : "Servicos e peças",
  "valor" : 950.0,
  "problemaDetectado" : null,
  "especialidadeNecessaria" : null,
  "inspetor" : null,
  "avaliacao" : 0.0,
  "pago" : false,
  "formaPagamento" : null,
  "id" : null
}, {
  "numeroOrdem" : "a3a0618e",
  "cliente" : null,
  "veiculo" : null,
  "servicos" : [ ],
  "responsavel" : null,
  "data" : "02/05/2024",
  "horario" : "14:34",
  "status" : "Pendente",
  "elevadorAlocado" : null,
  "itensUtilizados" : [ {
    "codigo" : "P002",
    "nome" : "Filtro de Óleo",
    "quantidade" : 30,
    "preco" : 25.0,
    "descricao" : "Filtro de óleo"
  } ],
  "tipo" : "Saída",
  "categoria" : "Despesa",
  "descricao" : "Compra de peças para ordem de serviço",
  "valor" : 750.0,
  "problemaDetectado" : null,
  "especialidadeNecessaria" : null,
  "inspetor" : null,
  "avaliacao" : 0.0,
  "pago" : false,
  "formaPagamento" : null,
  "id" : null
}, {
  "numeroOrdem" : null,
  "cliente" : {
    "nome" : "Pedro Oliveira",
    "telefone" : "",
    "endereco" : "",
    "clienteId" : "CLI0013",
    "veiculos" : [ ],
    "cpfAnonimizado" : ""
  },
  "veiculo" : null,
  "servicos" : [ {
    "nome" : "Revisão",
    "descricao" : "Revisão completa",
    "valor" : 300.0,
    "tempoEstimado" : 120,
    "requerElevador" : false
  } ],
  "responsavel" : {
    "nome" : "Paulo Suspensão",
    "telefone" : "",
    "endereco" : "",
    "cargo" : "Mecânico",
    "salario" : 0.0,
    "matricula" : "TEMP",
    "departamento" : "Temporário",
    "especialidades" : [ ],
    "isEspecialista" : false,
    "especialista" : false
  },
  "data" : "03/05/2024",
  "horario" : "11:00",
  "status" : "Concluído",
  "elevadorAlocado" : null,
  "itensUtilizados" : [ {
    "codigo" : "P003",
    "nome" : "Pastilha de Freio",
    "quantidade" : 40,
    "preco" : 80.0,
    "descricao" : "Pastilha de freio"
  } ],
  "tipo" : "Entrada",
  "categoria" : "Serviços",
  "descricao" : "Servicos e peças",
  "valor" : 3500.0,
  "problemaDetectado" : null,
  "especialidadeNecessaria" : null,
  "inspetor" : null,
  "avaliacao" : 0.0,
  "pago" : false,
  "formaPagamento" : null,
  "id" : null
}, {
  "numeroOrdem" : "99d8693b",
  "cliente" : null,
  "veiculo" : null,
  "servicos" : [ ],
  "responsavel" : null,
  "data" : "03/05/2024",
  "horario" : "14:34",
  "status" : "Pendente",
  "elevadorAlocado" : null,
  "itensUtilizados" : [ {
    "codigo" : "P003",
    "nome" : "Pastilha de Freio",
    "quantidade" : 40,
    "preco" : 80.0,
    "descricao" : "Pastilha de freio"
  } ],
  "tipo" : "Saída",
  "categoria" : "Despesa",
  "descricao" : "Compra de peças para ordem de serviço",
  "valor" : 3200.0,
  "problemaDetectado" : null,
  "especialidadeNecessaria" : null,
  "inspetor" : null,
  "avaliacao" : 0.0,
  "pago" : false,
  "formaPagamento" : null,
  "id" : null
}, {
  "numeroOrdem" : null,
  "cliente" : {
    "nome" : "Ana Costa",
    "telefone" : "",
    "endereco" : "",
    "clienteId" : "CLI0014",
    "veiculos" : [ ],
    "cpfAnonimizado" : ""
  },
  "veiculo" : null,
  "servicos" : [ {
    "nome" : "Troca de freios",
    "descricao" : "Troca de pastilhas e discos",
    "valor" : 400.0,
    "tempoEstimado" : 90,
    "requerElevador" : false
  } ],
  "responsavel" : {
    "nome" : "Ricardo Motor",
    "telefone" : "",
    "endereco" : "",
    "cargo" : "Mecânico",
    "salario" : 0.0,
    "matricula" : "TEMP",
    "departamento" : "Temporário",
    "especialidades" : [ ],
    "isEspecialista" : false,
    "especialista" : false
  },
  "data" : "04/05/2024",
  "horario" : "13:00",
  "status" : "Concluído",
  "elevadorAlocado" : null,
  "itensUtilizados" : [ {
    "codigo" : "P004",
    "nome" : "Bateria",
    "quantidade" : 20,
    "preco" : 350.0,
    "descricao" : "Bateria 60Ah"
  } ],
  "tipo" : "Entrada",
  "categoria" : "Serviços",
  "descricao" : "Servicos e peças",
  "valor" : 7400.0,
  "problemaDetectado" : null,
  "especialidadeNecessaria" : null,
  "inspetor" : null,
  "avaliacao" : 0.0,
  "pago" : false,
  "formaPagamento" : null,
  "id" : null
}, {
  "numeroOrdem" : "c39bcf18",
  "cliente" : null,
  "veiculo" : null,
  "servicos" : [ ],
  "responsavel" : null,
  "data" : "04/05/2024",
  "horario" : "14:34",
  "status" : "Pendente",
  "elevadorAlocado" : null,
  "itensUtilizados" : [ {
    "codigo" : "P004",
    "nome" : "Bateria",
    "quantidade" : 20,
    "preco" : 350.0,
    "descricao" : "Bateria 60Ah"
  } ],
  "tipo" : "Saída",
  "categoria" : "Despesa",
  "descricao" : "Compra de peças para ordem de serviço",
  "valor" : 7000.0,
  "problemaDetectado" : null,
  "especialidadeNecessaria" : null,
  "inspetor" : null,
  "avaliacao" : 0.0,
  "pago" : false,
  "formaPagamento" : null,
  "id" : null
}, {
  "numeroOrdem" : null,
  "cliente" : {
    "nome" : "Carlos Souza",
    "telefone" : "",
    "endereco" : "",
    "clienteId" : "CLI0015",
    "veiculos" : [ ],
    "cpfAnonimizado" : ""
  },
  "veiculo" : null,
  "servicos" : [ {
    "nome" : "Troca de suspensão",
    "descricao" : "Troca de amortecedores",
    "valor" : 800.0,
    "tempoEstimado" : 180,
    "requerElevador" : false
  } ],
  "responsavel" : {
    "nome" : "Marcos Freios",
    "telefone" : "",
    "endereco" : "",
    "cargo" : "Mecânico",
    "salario" : 0.0,
    "matricula" : "TEMP",
    "departamento" : "Temporário",
    "especialidades" : [ ],
    "isEspecialista" : false,
    "especialista" : false
  },
  "data" : "05/05/2024",
  "horario" : "14:00",
  "status" : "Concluído",
  "elevadorAlocado" : null,
  "itensUtilizados" : [ {
    "codigo" : "P005",
    "nome" : "Filtro de Ar",
    "quantidade" : 25,
    "preco" : 45.0,
    "descricao" : "Filtro de ar motor"
  } ],
  "tipo" : "Entrada",
  "categoria" : "Serviços",
  "descricao" : "Servicos e peças",
  "valor" : 1925.0,
  "problemaDetectado" : null,
  "especialidadeNecessaria" : null,
  "inspetor" : null,
  "avaliacao" : 0.0,
  "pago" : false,
  "formaPagamento" : null,
  "id" : null
}, {
  "numeroOrdem" : "4e863a17",
  "cliente" : null,
  "veiculo" : null,
  "servicos" : [ ],
  "responsavel" : null,
  "data" : "05/05/2024",
  "horario" : "14:34",
  "status" : "Pendente",
  "elevadorAlocado" : null,
  "itensUtilizados" : [ {
    "codigo" : "P005",
    "nome" : "Filtro de Ar",
    "quantidade" : 25,
    "preco" : 45.0,
    "descricao" : "Filtro de ar motor"
  } ],
  "tipo" : "Saída",
  "categoria" : "Despesa",
  "descricao" : "Compra de peças para ordem de serviço",
  "valor" : 1125.0,
  "problemaDetectado" : null,
  "especialidadeNecessaria" : null,
  "inspetor" : null,
  "avaliacao" : 0.0,
  "pago" : false,
  "formaPagamento" : null,
  "id" : null
}, {
  "numeroOrdem" : "c92cc9a4",
  "cliente" : null,
  "veiculo" : null,
  "servicos" : [ ],
  "responsavel" : null,
  "data" : "25/05/2024",
  "horario" : "14:34",
  "status" : "Pendente",
  "elevadorAlocado" : null,
  "itensUtilizados" : [ {
    "codigo" : "P002",
    "nome" : "Filtro de Óleo",
    "quantidade" : 20,
    "preco" : 25.0,
    "descricao" : "Filtro de óleo"
  } ],
  "tipo" : "Entrada",
  "categoria" : "Vendas",
  "descricao" : "Venda de peças - Filtro de óleo",
  "valor" : 500.0,
  "problemaDetectado" : null,
  "especialidadeNecessaria" : null,
  "inspetor" : null,
  "avaliacao" : 0.0,
  "pago" : false,
  "formaPagamento" : null,
  "id" : null
}, {
  "numeroOrdem" : "94f09ba5",
  "cliente" : null,
  "veiculo" : null,
  "servicos" : [ ],
  "responsavel" : null,
  "data" : "28/05/2024",
  "horario" : "14:34",
  "status" : "Pendente",
  "elevadorAlocado" : null,
  "itensUtilizados" : [ {
    "codigo" : "P004",
    "nome" : "Bateria",
    "quantidade" : 3,
    "preco" : 350.0,
    "descricao" : "Bateria 60Ah"
  } ],
  "tipo" : "Entrada",
  "categoria" : "Vendas",
  "descricao" : "Venda de peças - Baterias",
  "valor" : 1050.0,
  "problemaDetectado" : null,
  "especialidadeNecessaria" : null,
  "inspetor" : null,
  "avaliacao" : 0.0,
  "pago" : false,
  "formaPagamento" : null,
  "id" : null
}, {
  "numeroOrdem" : "2448116b",
  "cliente" : null,
  "veiculo" : null,
  "servicos" : [ ],
  "responsavel" : null,
  "data" : "30/05/2024",
  "horario" : "14:34",
  "status" : "Pendente",
  "elevadorAlocado" : null,
  "itensUtilizados" : [ {
    "codigo" : "P001",
    "nome" : "Óleo Motor",
    "quantidade" : 20,
    "preco" : 35.0,
    "descricao" : "Óleo sintético 5W30"
  } ],
  "tipo" : "Entrada",
  "categoria" : "Vendas",
  "descricao" : "Venda de peças - Óleo Motor",
  "valor" : 700.0,
  "problemaDetectado" : null,
  "especialidadeNecessaria" : null,
  "inspetor" : null,
  "avaliacao" : 0.0,
  "pago" : false,
  "formaPagamento" : null,
  "id" : null
}, {
  "numeroOrdem" : "ddcb9c62",
  "cliente" : null,
  "veiculo" : null,
  "servicos" : [ ],
  "responsavel" : null,
  "data" : "15/05/2024",
  "horario" : "14:34",
  "status" : "Pendente",
  "elevadorAlocado" : null,
  "itensUtilizados" : [ ],
  "tipo" : "Saída",
  "categoria" : "Despesas Administrativas",
  "descricao" : "Compra de material de limpeza",
  "valor" : 0.0,
  "problemaDetectado" : null,
  "especialidadeNecessaria" : null,
  "inspetor" : null,
  "avaliacao" : 0.0,
  "pago" : false,
  "formaPagamento" : null,
  "id" : null
}, {
  "numeroOrdem" : "b73deb62",
  "cliente" : null,
  "veiculo" : null,
  "servicos" : [ ],
  "responsavel" : null,
  "data" : "20/05/2024",
  "horario" : "14:34",
  "status" : "Pendente",
  "elevadorAlocado" : null,
  "itensUtilizados" : [ ],
  "tipo" : "Saída",
  "categoria" : "Despesas Administrativas",
  "descricao" : "Compra de café e lanches",
  "valor" : 0.0,
  "problemaDetectado" : null,
  "especialidadeNecessaria" : null,
  "inspetor" : null,
  "avaliacao" : 0.0,
  "pago" : false,
  "formaPagamento" : null,
  "id" : null
}, {
  "numeroOrdem" : "454d85a8",
  "cliente" : null,
  "veiculo" : null,
  "servicos" : [ ],
  "responsavel" : null,
  "data" : "22/05/2024",
  "horario" : "14:34",
  "status" : "Pendente",
  "elevadorAlocado" : null,
  "itensUtilizados" : [ ],
  "tipo" : "Saída",
  "categoria" : "Despesas Administrativas",
  "descricao" : "Compra de uniformes",
  "valor" : 0.0,
  "problemaDetectado" : null,
  "especialidadeNecessaria" : null,
  "inspetor" : null,
  "avaliacao" : 0.0,
  "pago" : false,
  "formaPagamento" : null,
  "id" : null
}, {
  "numeroOrdem" : "00e1d093",
  "cliente" : null,
  "veiculo" : null,
  "servicos" : [ ],
  "responsavel" : null,
  "data" : "25/05/2024",
  "horario" : "14:34",
  "status" : "Pendente",
  "elevadorAlocado" : null,
  "itensUtilizados" : [ ],
  "tipo" : "Saída",
  "categoria" : "Despesas Administrativas",
  "descricao" : "Manutenção de equipamentos",
  "valor" : 0.0,
  "problemaDetectado" : null,
  "especialidadeNecessaria" : null,
  "inspetor" : null,
  "avaliacao" : 0.0,
  "pago" : false,
  "formaPagamento" : null,
  "id" : null
}, {
  "numeroOrdem" : "502947b5",
  "cliente" : null,
  "veiculo" : null,
  "servicos" : [ ],
  "responsavel" : null,
  "data" : "31/05/2024",
  "horario" : "14:34",
  "status" : "Pendente",
  "elevadorAlocado" : null,
  "itensUtilizados" : [ ],
  "tipo" : "Saída",
  "categoria" : "Folha de Pagamento",
  "descricao" : "Pagamento de salários - Maio/2024",
  "valor" : 0.0,
  "problemaDetectado" : null,
  "especialidadeNecessaria" : null,
  "inspetor" : null,
  "avaliacao" : 0.0,
  "pago" : false,
  "formaPagamento" : null,
  "id" : null
}, {
  "numeroOrdem" : "f3065a2f",
  "cliente" : null,
  "veiculo" : null,
  "servicos" : [ ],
  "responsavel" : null,
  "data" : "05/05/2024",
  "horario" : "14:34",
  "status" : "Pendente",
  "elevadorAlocado" : null,
  "itensUtilizados" : [ {
    "codigo" : "P001",
    "nome" : "Óleo Motor",
    "quantidade" : 100,
    "preco" : 30.0,
    "descricao" : "Óleo sintético 5W30"
  } ],
  "tipo" : "Saída",
  "categoria" : "Compras",
  "descricao" : "Compra de estoque - Óleos e filtros",
  "valor" : 3000.0,
  "problemaDetectado" : null,
  "especialidadeNecessaria" : null,
  "inspetor" : null,
  "avaliacao" : 0.0,
  "pago" : false,
  "formaPagamento" : null,
  "id" : null
}, {
  "numeroOrdem" : "40ad90fa",
  "cliente" : null,
  "veiculo" : null,
  "servicos" : [ ],
  "responsavel" : null,
  "data" : "10/05/2024",
  "horario" : "14:34",
  "status" : "Pendente",
  "elevadorAlocado" : null,
  "itensUtilizados" : [ {
    "codigo" : "P003",
    "nome" : "Pastilha de Freio",
    "quantidade" : 50,
    "preco" : 70.0,
    "descricao" : "Pastilha de freio"
  } ],
  "tipo" : "Saída",
  "categoria" : "Compras",
  "descricao" : "Compra de estoque - Peças de freio",
  "valor" : 3500.0,
  "problemaDetectado" : null,
  "especialidadeNecessaria" : null,
  "inspetor" : null,
  "avaliacao" : 0.0,
  "pago" : false,
  "formaPagamento" : null,
  "id" : null
}, {
  "numeroOrdem" : "811c5a77",
  "cliente" : null,
  "veiculo" : null,
  "servicos" : [ ],
  "responsavel" : null,
  "data" : "15/05/2024",
  "horario" : "14:34",
  "status" : "Pendente",
  "elevadorAlocado" : null,
  "itensUtilizados" : [ {
    "codigo" : "P004",
    "nome" : "Bateria",
    "quantidade" : 20,
    "preco" : 320.0,
    "descricao" : "Bateria 60Ah"
  } ],
  "tipo" : "Saída",
  "categoria" : "Compras",
  "descricao" : "Compra de estoque - Baterias",
  "valor" : 6400.0,
  "problemaDetectado" : null,
  "especialidadeNecessaria" : null,
  "inspetor" : null,
  "avaliacao" : 0.0,
  "pago" : false,
  "formaPagamento" : null,
  "id" : null
}, {
  "numeroOrdem" : "0fb45411",
  "cliente" : null,
  "veiculo" : null,
  "servicos" : [ ],
  "responsavel" : null,
  "data" : "12/05/2024",
  "horario" : "14:34",
  "status" : "Pendente",
  "elevadorAlocado" : null,
  "itensUtilizados" : [ ],
  "tipo" : "Entrada",
  "categoria" : "Serviços Especializados",
  "descricao" : "Serviço de diagnóstico eletrônico",
  "valor" : 0.0,
  "problemaDetectado" : null,
  "especialidadeNecessaria" : null,
  "inspetor" : null,
  "avaliacao" : 0.0,
  "pago" : false,
  "formaPagamento" : null,
  "id" : null
}, {
  "numeroOrdem" : "abbfa692",
  "cliente" : null,
  "veiculo" : null,
  "servicos" : [ ],
  "responsavel" : null,
  "data" : "18/05/2024",
  "horario" : "14:34",
  "status" : "Pendente",
  "elevadorAlocado" : null,
  "itensUtilizados" : [ ],
  "tipo" : "Entrada",
  "categoria" : "Serviços Especializados",
  "descricao" : "Serviço de pintura automotiva",
  "valor" : 0.0,
  "problemaDetectado" : null,
  "especialidadeNecessaria" : null,
  "inspetor" : null,
  "avaliacao" : 0.0,
  "pago" : false,
  "formaPagamento" : null,
  "id" : null
}, {
  "numeroOrdem" : "66d6a28e",
  "cliente" : null,
  "veiculo" : null,
  "servicos" : [ ],
  "responsavel" : null,
  "data" : "24/05/2024",
  "horario" : "14:34",
  "status" : "Pendente",
  "elevadorAlocado" : null,
  "itensUtilizados" : [ ],
  "tipo" : "Entrada",
  "categoria" : "Serviços Especializados",
  "descricao" : "Serviço de funilaria",
  "valor" : 0.0,
  "problemaDetectado" : null,
  "especialidadeNecessaria" : null,
  "inspetor" : null,
  "avaliacao" : 0.0,
  "pago" : false,
  "formaPagamento" : null,
  "id" : null
}, {
  "numeroOrdem" : "7f65bcbc",
  "cliente" : null,
  "veiculo" : null,
  "servicos" : [ ],
  "responsavel" : null,
  "data" : "01/05/2024",
  "horario" : "14:34",
  "status" : "Pendente",
  "elevadorAlocado" : null,
  "itensUtilizados" : [ ],
  "tipo" : "Saída",
  "categoria" : "Despesas Operacionais",
  "descricao" : "Aluguel da oficina",
  "valor" : 0.0,
  "problemaDetectado" : null,
  "especialidadeNecessaria" : null,
  "inspetor" : null,
  "avaliacao" : 0.0,
  "pago" : false,
  "formaPagamento" : null,
  "id" : null
}, {
  "numeroOrdem" : "14de8687",
  "cliente" : null,
  "veiculo" : null,
  "servicos" : [ ],
  "responsavel" : null,
  "data" : "10/05/2024",
  "horario" : "14:34",
  "status" : "Pendente",
  "elevadorAlocado" : null,
  "itensUtilizados" : [ ],
  "tipo" : "Saída",
  "categoria" : "Despesas Operacionais",
  "descricao" : "Conta de energia elétrica",
  "valor" : 0.0,
  "problemaDetectado" : null,
  "especialidadeNecessaria" : null,
  "inspetor" : null,
  "avaliacao" : 0.0,
  "pago" : false,
  "formaPagamento" : null,
  "id" : null
}, {
  "numeroOrdem" : "87595662",
  "cliente" : null,
  "veiculo" : null,
  "servicos" : [ ],
  "responsavel" : null,
  "data" : "10/05/2024",
  "horario" : "14:34",
  "status" : "Pendente",
  "elevadorAlocado" : null,
  "itensUtilizados" : [ ],
  "tipo" : "Saída",
  "categoria" : "Despesas Operacionais",
  "descricao" : "Conta de água",
  "valor" : 0.0,
  "problemaDetectado" : null,
  "especialidadeNecessaria" : null,
  "inspetor" : null,
  "avaliacao" : 0.0,
  "pago" : false,
  "formaPagamento" : null,
  "id" : null
}, {
  "numeroOrdem" : "7bac8650",
  "cliente" : null,
  "veiculo" : null,
  "servicos" : [ ],
  "responsavel" : null,
  "data" : "15/05/2024",
  "horario" : "14:34",
  "status" : "Pendente",
  "elevadorAlocado" : null,
  "itensUtilizados" : [ ],
  "tipo" : "Saída",
  "categoria" : "Despesas Operacionais",
  "descricao" : "Internet e telefone",
  "valor" : 0.0,
  "problemaDetectado" : null,
  "especialidadeNecessaria" : null,
  "inspetor" : null,
  "avaliacao" : 0.0,
  "pago" : false,
  "formaPagamento" : null,
  "id" : null
}, {
  "numeroOrdem" : "78de1dad",
  "cliente" : null,
  "veiculo" : null,
  "servicos" : [ ],
  "responsavel" : null,
  "data" : "03/05/2024",
  "horario" : "14:34",
  "status" : "Pendente",
  "elevadorAlocado" : null,
  "itensUtilizados" : [ ],
  "tipo" : "Entrada",
  "categoria" : "Taxas",
  "descricao" : "Taxa de diagnóstico",
  "valor" : 0.0,
  "problemaDetectado" : null,
  "especialidadeNecessaria" : null,
  "inspetor" : null,
  "avaliacao" : 0.0,
  "pago" : false,
  "formaPagamento" : null,
  "id" : null
}, {
  "numeroOrdem" : "3039929d",
  "cliente" : null,
  "veiculo" : null,
  "servicos" : [ ],
  "responsavel" : null,
  "data" : "07/05/2024",
  "horario" : "14:34",
  "status" : "Pendente",
  "elevadorAlocado" : null,
  "itensUtilizados" : [ ],
  "tipo" : "Entrada",
  "categoria" : "Taxas",
  "descricao" : "Taxa de diagnóstico",
  "valor" : 0.0,
  "problemaDetectado" : null,
  "especialidadeNecessaria" : null,
  "inspetor" : null,
  "avaliacao" : 0.0,
  "pago" : false,
  "formaPagamento" : null,
  "id" : null
}, {
  "numeroOrdem" : "345ca498",
  "cliente" : null,
  "veiculo" : null,
  "servicos" : [ ],
  "responsavel" : null,
  "data" : "14/05/2024",
  "horario" : "14:34",
  "status" : "Pendente",
  "elevadorAlocado" : null,
  "itensUtilizados" : [ ],
  "tipo" : "Entrada",
  "categoria" : "Taxas",
  "descricao" : "Taxa de diagnóstico",
  "valor" : 0.0,
  "problemaDetectado" : null,
  "especialidadeNecessaria" : null,
  "inspetor" : null,
  "avaliacao" : 0.0,
  "pago" : false,
  "formaPagamento" : null,
  "id" : null
}, {
  "numeroOrdem" : "710eb465",
  "cliente" : null,
  "veiculo" : null,
  "servicos" : [ ],
  "responsavel" : null,
  "data" : "21/05/2024",
  "horario" : "14:34",
  "status" : "Pendente",
  "elevadorAlocado" : null,
  "itensUtilizados" : [ ],
  "tipo" : "Entrada",
  "categoria" : "Taxas",
  "descricao" : "Taxa de diagnóstico",
  "valor" : 0.0,
  "problemaDetectado" : null,
  "especialidadeNecessaria" : null,
  "inspetor" : null,
  "avaliacao" : 0.0,
  "pago" : false,
  "formaPagamento" : null,
  "id" : null
}, {
  "numeroOrdem" : "a590549e",
  "cliente" : null,
  "veiculo" : null,
  "servicos" : [ ],
  "responsavel" : null,
  "data" : "08/05/2024",
  "horario" : "14:34",
  "status" : "Pendente",
  "elevadorAlocado" : null,
  "itensUtilizados" : [ ],
  "tipo" : "Saída",
  "categoria" : "Fornecedores",
  "descricao" : "Pagamento fornecedor - Auto Peças Silva",
  "valor" : 0.0,
  "problemaDetectado" : null,
  "especialidadeNecessaria" : null,
  "inspetor" : null,
  "avaliacao" : 0.0,
  "pago" : false,
  "formaPagamento" : null,
  "id" : null
}, {
  "numeroOrdem" : "04f8ed70",
  "cliente" : null,
  "veiculo" : null,
  "servicos" : [ ],
  "responsavel" : null,
  "data" : "16/05/2024",
  "horario" : "14:34",
  "status" : "Pendente",
  "elevadorAlocado" : null,
  "itensUtilizados" : [ ],
  "tipo" : "Saída",
  "categoria" : "Fornecedores",
  "descricao" : "Pagamento fornecedor - Mecânica Express",
  "valor" : 0.0,
  "problemaDetectado" : null,
  "especialidadeNecessaria" : null,
  "inspetor" : null,
  "avaliacao" : 0.0,
  "pago" : false,
  "formaPagamento" : null,
  "id" : null
}, {
  "numeroOrdem" : "ccbdb2e8",
  "cliente" : null,
  "veiculo" : null,
  "servicos" : [ ],
  "responsavel" : null,
  "data" : "23/05/2024",
  "horario" : "14:34",
  "status" : "Pendente",
  "elevadorAlocado" : null,
  "itensUtilizados" : [ ],
  "tipo" : "Saída",
  "categoria" : "Fornecedores",
  "descricao" : "Pagamento fornecedor - Peças Premium",
  "valor" : 0.0,
  "problemaDetectado" : null,
  "especialidadeNecessaria" : null,
  "inspetor" : null,
  "avaliacao" : 0.0,
  "pago" : false,
  "formaPagamento" : null,
  "id" : null
}, {
  "numeroOrdem" : "1fdfabe8",
  "cliente" : null,
  "veiculo" : null,
  "servicos" : [ ],
  "responsavel" : null,
  "data" : "11/05/2024",
  "horario" : "14:34",
  "status" : "Pendente",
  "elevadorAlocado" : null,
  "itensUtilizados" : [ ],
  "tipo" : "Entrada",
  "categoria" : "Serviços Premium",
  "descricao" : "Revisão completa - Veículo de luxo",
  "valor" : 0.0,
  "problemaDetectado" : null,
  "especialidadeNecessaria" : null,
  "inspetor" : null,
  "avaliacao" : 0.0,
  "pago" : false,
  "formaPagamento" : null,
  "id" : null
}, {
  "numeroOrdem" : "e945411f",
  "cliente" : null,
  "veiculo" : null,
  "servicos" : [ ],
  "responsavel" : null,
  "data" : "19/05/2024",
  "horario" : "14:34",
  "status" : "Pendente",
  "elevadorAlocado" : null,
  "itensUtilizados" : [ ],
  "tipo" : "Entrada",
  "categoria" : "Serviços Premium",
  "descricao" : "Manutenção preventiva - Frota empresarial",
  "valor" : 0.0,
  "problemaDetectado" : null,
  "especialidadeNecessaria" : null,
  "inspetor" : null,
  "avaliacao" : 0.0,
  "pago" : false,
  "formaPagamento" : null,
  "id" : null
}, {
  "numeroOrdem" : "ccfaf057",
  "cliente" : null,
  "veiculo" : null,
  "servicos" : [ ],
  "responsavel" : null,
  "data" : "26/05/2024",
  "horario" : "14:34",
  "status" : "Pendente",
  "elevadorAlocado" : null,
  "itensUtilizados" : [ ],
  "tipo" : "Entrada",
  "categoria" : "Serviços Premium",
  "descricao" : "Reparo de motor - Veículo antigo",
  "valor" : 0.0,
  "problemaDetectado" : null,
  "especialidadeNecessaria" : null,
  "inspetor" : null,
  "avaliacao" : 0.0,
  "pago" : false,
  "formaPagamento" : null,
  "id" : null
}, {
  "numeroOrdem" : "a6bbc189",
  "cliente" : null,
  "veiculo" : null,
  "servicos" : [ ],
  "responsavel" : null,
  "data" : "06/05/2024",
  "horario" : "14:34",
  "status" : "Pendente",
  "elevadorAlocado" : null,
  "itensUtilizados" : [ ],
  "tipo" : "Saída",
  "categoria" : "Marketing",
  "descricao" : "Anúncios em jornais locais",
  "valor" : 0.0,
  "problemaDetectado" : null,
  "especialidadeNecessaria" : null,
  "inspetor" : null,
  "avaliacao" : 0.0,
  "pago" : false,
  "formaPagamento" : null,
  "id" : null
}, {
  "numeroOrdem" : "0befcaa0",
  "cliente" : null,
  "veiculo" : null,
  "servicos" : [ ],
  "responsavel" : null,
  "data" : "13/05/2024",
  "horario" : "14:34",
  "status" : "Pendente",
  "elevadorAlocado" : null,
  "itensUtilizados" : [ ],
  "tipo" : "Saída",
  "categoria" : "Marketing",
  "descricao" : "Panfletos e material promocional",
  "valor" : 0.0,
  "problemaDetectado" : null,
  "especialidadeNecessaria" : null,
  "inspetor" : null,
  "avaliacao" : 0.0,
  "pago" : false,
  "formaPagamento" : null,
  "id" : null
}, {
  "numeroOrdem" : "faac972c",
  "cliente" : null,
  "veiculo" : null,
  "servicos" : [ ],
  "responsavel" : null,
  "data" : "20/05/2024",
  "horario" : "14:34",
  "status" : "Pendente",
  "elevadorAlocado" : null,
  "itensUtilizados" : [ ],
  "tipo" : "Saída",
  "categoria" : "Marketing",
  "descricao" : "Manutenção do site e redes sociais",
  "valor" : 0.0,
  "problemaDetectado" : null,
  "especialidadeNecessaria" : null,
  "inspetor" : null,
  "avaliacao" : 0.0,
  "pago" : false,
  "formaPagamento" : null,
  "id" : null
}, {
  "numeroOrdem" : "aa2dbd3f",
  "cliente" : null,
  "veiculo" : null,
  "servicos" : [ ],
  "responsavel" : null,
  "data" : "09/05/2024",
  "horario" : "14:34",
  "status" : "Pendente",
  "elevadorAlocado" : null,
  "itensUtilizados" : [ ],
  "tipo" : "Entrada",
  "categoria" : "Consultoria",
  "descricao" : "Consultoria técnica - Cliente empresarial",
  "valor" : 0.0,
  "problemaDetectado" : null,
  "especialidadeNecessaria" : null,
  "inspetor" : null,
  "avaliacao" : 0.0,
  "pago" : false,
  "formaPagamento" : null,
  "id" : null
}, {
  "numeroOrdem" : "68de56b5",
  "cliente" : null,
  "veiculo" : null,
  "servicos" : [ ],
  "responsavel" : null,
  "data" : "17/05/2024",
  "horario" : "14:34",
  "status" : "Pendente",
  "elevadorAlocado" : null,
  "itensUtilizados" : [ ],
  "tipo" : "Entrada",
  "categoria" : "Consultoria",
  "descricao" : "Avaliação de frota - Empresa de transporte",
  "valor" : 0.0,
  "problemaDetectado" : null,
  "especialidadeNecessaria" : null,
  "inspetor" : null,
  "avaliacao" : 0.0,
  "pago" : false,
  "formaPagamento" : null,
  "id" : null
}, {
  "numeroOrdem" : "5841fee8",
  "cliente" : null,
  "veiculo" : null,
  "servicos" : [ ],
  "responsavel" : null,
  "data" : "29/05/2024",
  "horario" : "14:34",
  "status" : "Pendente",
  "elevadorAlocado" : null,
  "itensUtilizados" : [ ],
  "tipo" : "Entrada",
  "categoria" : "Consultoria",
  "descricao" : "Relatório técnico - Seguradora",
  "valor" : 0.0,
  "problemaDetectado" : null,
  "especialidadeNecessaria" : null,
  "inspetor" : null,
  "avaliacao" : 0.0,
  "pago" : false,
  "formaPagamento" : null,
  "id" : null
}, {
  "numeroOrdem" : "d164cb1a",
  "cliente" : null,
  "veiculo" : null,
  "servicos" : [ ],
  "responsavel" : null,
  "data" : "04/05/2024",
  "horario" : "14:34",
  "status" : "Pendente",
  "elevadorAlocado" : null,
  "itensUtilizados" : [ ],
  "tipo" : "Saída",
  "categoria" : "Segurança",
  "descricao" : "Sistema de alarme e câmeras",
  "valor" : 0.0,
  "problemaDetectado" : null,
  "especialidadeNecessaria" : null,
  "inspetor" : null,
  "avaliacao" : 0.0,
  "pago" : false,
  "formaPagamento" : null,
  "id" : null
}, {
  "numeroOrdem" : "18a7b9ec",
  "cliente" : null,
  "veiculo" : null,
  "servicos" : [ ],
  "responsavel" : null,
  "data" : "12/05/2024",
  "horario" : "14:34",
  "status" : "Pendente",
  "elevadorAlocado" : null,
  "itensUtilizados" : [ ],
  "tipo" : "Saída",
  "categoria" : "Segurança",
  "descricao" : "Manutenção de extintores",
  "valor" : 0.0,
  "problemaDetectado" : null,
  "especialidadeNecessaria" : null,
  "inspetor" : null,
  "avaliacao" : 0.0,
  "pago" : false,
  "formaPagamento" : null,
  "id" : null
}, {
  "numeroOrdem" : "b3876d0d",
  "cliente" : null,
  "veiculo" : null,
  "servicos" : [ ],
  "responsavel" : null,
  "data" : "27/05/2024",
  "horario" : "14:34",
  "status" : "Pendente",
  "elevadorAlocado" : null,
  "itensUtilizados" : [ ],
  "tipo" : "Saída",
  "categoria" : "Segurança",
  "descricao" : "Treinamento de segurança",
  "valor" : 0.0,
  "problemaDetectado" : null,
  "especialidadeNecessaria" : null,
  "inspetor" : null,
  "avaliacao" : 0.0,
  "pago" : false,
  "formaPagamento" : null,
  "id" : null
}, {
  "numeroOrdem" : "b3888da9",
  "cliente" : null,
  "veiculo" : null,
  "servicos" : [ ],
  "responsavel" : null,
  "data" : "14/05/2024",
  "horario" : "14:34",
  "status" : "Pendente",
  "elevadorAlocado" : null,
  "itensUtilizados" : [ ],
  "tipo" : "Entrada",
  "categoria" : "Educação",
  "descricao" : "Curso de mecânica básica",
  "valor" : 0.0,
  "problemaDetectado" : null,
  "especialidadeNecessaria" : null,
  "inspetor" : null,
  "avaliacao" : 0.0,
  "pago" : false,
  "formaPagamento" : null,
  "id" : null
}, {
  "numeroOrdem" : "c6cde519",
  "cliente" : null,
  "veiculo" : null,
  "servicos" : [ ],
  "responsavel" : null,
  "data" : "28/05/2024",
  "horario" : "14:34",
  "status" : "Pendente",
  "elevadorAlocado" : null,
  "itensUtilizados" : [ ],
  "tipo" : "Entrada",
  "categoria" : "Educação",
  "descricao" : "Workshop de manutenção preventiva",
  "valor" : 0.0,
  "problemaDetectado" : null,
  "especialidadeNecessaria" : null,
  "inspetor" : null,
  "avaliacao" : 0.0,
  "pago" : false,
  "formaPagamento" : null,
  "id" : null
}, {
  "numeroOrdem" : "ff63ad08",
  "cliente" : null,
  "veiculo" : null,
  "servicos" : [ ],
  "responsavel" : null,
  "data" : "11/05/2024",
  "horario" : "14:34",
  "status" : "Pendente",
  "elevadorAlocado" : null,
  "itensUtilizados" : [ ],
  "tipo" : "Saída",
  "categoria" : "Treinamento",
  "descricao" : "Treinamento técnico - Funcionários",
  "valor" : 0.0,
  "problemaDetectado" : null,
  "especialidadeNecessaria" : null,
  "inspetor" : null,
  "avaliacao" : 0.0,
  "pago" : false,
  "formaPagamento" : null,
  "id" : null
}, {
  "numeroOrdem" : "2ad77405",
  "cliente" : null,
  "veiculo" : null,
  "servicos" : [ ],
  "responsavel" : null,
  "data" : "25/05/2024",
  "horario" : "14:34",
  "status" : "Pendente",
  "elevadorAlocado" : null,
  "itensUtilizados" : [ ],
  "tipo" : "Saída",
  "categoria" : "Treinamento",
  "descricao" : "Certificação técnica - Mecânicos",
  "valor" : 0.0,
  "problemaDetectado" : null,
  "especialidadeNecessaria" : null,
  "inspetor" : null,
  "avaliacao" : 0.0,
  "pago" : false,
  "formaPagamento" : null,
  "id" : null
}, {
  "numeroOrdem" : "b33e1648",
  "cliente" : null,
  "veiculo" : null,
  "servicos" : [ ],
  "responsavel" : null,
  "data" : "16/05/2024",
  "horario" : "14:34",
  "status" : "Pendente",
  "elevadorAlocado" : null,
  "itensUtilizados" : [ ],
  "tipo" : "Entrada",
  "categoria" : "Aluguel",
  "descricao" : "Aluguel de elevador - Mecânico externo",
  "valor" : 0.0,
  "problemaDetectado" : null,
  "especialidadeNecessaria" : null,
  "inspetor" : null,
  "avaliacao" : 0.0,
  "pago" : false,
  "formaPagamento" : null,
  "id" : null
}, {
  "numeroOrdem" : "d043290d",
  "cliente" : null,
  "veiculo" : null,
  "servicos" : [ ],
  "responsavel" : null,
  "data" : "22/05/2024",
  "horario" : "14:34",
  "status" : "Pendente",
  "elevadorAlocado" : null,
  "itensUtilizados" : [ ],
  "tipo" : "Entrada",
  "categoria" : "Aluguel",
  "descricao" : "Aluguel de ferramentas especiais",
  "valor" : 0.0,
  "problemaDetectado" : null,
  "especialidadeNecessaria" : null,
  "inspetor" : null,
  "avaliacao" : 0.0,
  "pago" : false,
  "formaPagamento" : null,
  "id" : null
}, {
  "numeroOrdem" : "b481cb26",
  "cliente" : null,
  "veiculo" : null,
  "servicos" : [ ],
  "responsavel" : null,
  "data" : "07/05/2024",
  "horario" : "14:34",
  "status" : "Pendente",
  "elevadorAlocado" : null,
  "itensUtilizados" : [ ],
  "tipo" : "Saída",
  "categoria" : "Manutenção de Equipamentos",
  "descricao" : "Manutenção de elevadores",
  "valor" : 0.0,
  "problemaDetectado" : null,
  "especialidadeNecessaria" : null,
  "inspetor" : null,
  "avaliacao" : 0.0,
  "pago" : false,
  "formaPagamento" : null,
  "id" : null
}, {
  "numeroOrdem" : "3535f1de",
  "cliente" : null,
  "veiculo" : null,
  "servicos" : [ ],
  "responsavel" : null,
  "data" : "21/05/2024",
  "horario" : "14:34",
  "status" : "Pendente",
  "elevadorAlocado" : null,
  "itensUtilizados" : [ ],
  "tipo" : "Saída",
  "categoria" : "Manutenção de Equipamentos",
  "descricao" : "Calibração de equipamentos",
  "valor" : 0.0,
  "problemaDetectado" : null,
  "especialidadeNecessaria" : null,
  "inspetor" : null,
  "avaliacao" : 0.0,
  "pago" : false,
  "formaPagamento" : null,
  "id" : null
}, {
  "numeroOrdem" : "44063280",
  "cliente" : null,
  "veiculo" : null,
  "servicos" : [ ],
  "responsavel" : null,
  "data" : "13/05/2024",
  "horario" : "14:34",
  "status" : "Pendente",
  "elevadorAlocado" : null,
  "itensUtilizados" : [ ],
  "tipo" : "Entrada",
  "categoria" : "Comissões",
  "descricao" : "Comissão de seguro automotivo",
  "valor" : 0.0,
  "problemaDetectado" : null,
  "especialidadeNecessaria" : null,
  "inspetor" : null,
  "avaliacao" : 0.0,
  "pago" : false,
  "formaPagamento" : null,
  "id" : null
}, {
  "numeroOrdem" : "90f78fe3",
  "cliente" : null,
  "veiculo" : null,
  "servicos" : [ ],
  "responsavel" : null,
  "data" : "27/05/2024",
  "horario" : "14:34",
  "status" : "Pendente",
  "elevadorAlocado" : null,
  "itensUtilizados" : [ ],
  "tipo" : "Entrada",
  "categoria" : "Comissões",
  "descricao" : "Comissão de seguro automotivo",
  "valor" : 0.0,
  "problemaDetectado" : null,
  "especialidadeNecessaria" : null,
  "inspetor" : null,
  "avaliacao" : 0.0,
  "pago" : false,
  "formaPagamento" : null,
  "id" : null
}, {
  "numeroOrdem" : "eb1a1ff3",
  "cliente" : null,
  "veiculo" : null,
  "servicos" : [ ],
  "responsavel" : null,
  "data" : "02/05/2024",
  "horario" : "14:34",
  "status" : "Pendente",
  "elevadorAlocado" : null,
  "itensUtilizados" : [ ],
  "tipo" : "Saída",
  "categoria" : "Seguros",
  "descricao" : "Seguro da oficina",
  "valor" : 0.0,
  "problemaDetectado" : null,
  "especialidadeNecessaria" : null,
  "inspetor" : null,
  "avaliacao" : 0.0,
  "pago" : false,
  "formaPagamento" : null,
  "id" : null
}, {
  "numeroOrdem" : "8e3328a5",
  "cliente" : null,
  "veiculo" : null,
  "servicos" : [ ],
  "responsavel" : null,
  "data" : "15/05/2024",
  "horario" : "14:34",
  "status" : "Pendente",
  "elevadorAlocado" : null,
  "itensUtilizados" : [ ],
  "tipo" : "Saída",
  "categoria" : "Seguros",
  "descricao" : "Seguro dos funcionários",
  "valor" : 0.0,
  "problemaDetectado" : null,
  "especialidadeNecessaria" : null,
  "inspetor" : null,
  "avaliacao" : 0.0,
  "pago" : false,
  "formaPagamento" : null,
  "id" : null
}, {
  "numeroOrdem" : "1417f92c",
  "cliente" : null,
  "veiculo" : null,
  "servicos" : [ ],
  "responsavel" : null,
  "data" : "18/05/2024",
  "horario" : "14:34",
  "status" : "Pendente",
  "elevadorAlocado" : null,
  "itensUtilizados" : [ ],
  "tipo" : "Entrada",
  "categoria" : "Parcerias",
  "descricao" : "Comissão de parceria - Auto Center",
  "valor" : 0.0,
  "problemaDetectado" : null,
  "especialidadeNecessaria" : null,
  "inspetor" : null,
  "avaliacao" : 0.0,
  "pago" : false,
  "formaPagamento" : null,
  "id" : null
}, {
  "numeroOrdem" : "11b3255c",
  "cliente" : null,
  "veiculo" : null,
  "servicos" : [ ],
  "responsavel" : null,
  "data" : "30/05/2024",
  "horario" : "14:34",
  "status" : "Pendente",
  "elevadorAlocado" : null,
  "itensUtilizados" : [ ],
  "tipo" : "Entrada",
  "categoria" : "Parcerias",
  "descricao" : "Comissão de parceria - Lava Jato",
  "valor" : 0.0,
  "problemaDetectado" : null,
  "especialidadeNecessaria" : null,
  "inspetor" : null,
  "avaliacao" : 0.0,
  "pago" : false,
  "formaPagamento" : null,
  "id" : null
}, {
  "numeroOrdem" : "d8a46f49",
  "cliente" : null,
  "veiculo" : null,
  "servicos" : [ ],
  "responsavel" : null,
  "data" : "10/05/2024",
  "horario" : "14:34",
  "status" : "Pendente",
  "elevadorAlocado" : null,
  "itensUtilizados" : [ ],
  "tipo" : "Saída",
  "categoria" : "Impostos",
  "descricao" : "Impostos municipais",
  "valor" : 0.0,
  "problemaDetectado" : null,
  "especialidadeNecessaria" : null,
  "inspetor" : null,
  "avaliacao" : 0.0,
  "pago" : false,
  "formaPagamento" : null,
  "id" : null
}, {
  "numeroOrdem" : "e1196b3a",
  "cliente" : null,
  "veiculo" : null,
  "servicos" : [ ],
  "responsavel" : null,
  "data" : "20/05/2024",
  "horario" : "14:34",
  "status" : "Pendente",
  "elevadorAlocado" : null,
  "itensUtilizados" : [ ],
  "tipo" : "Saída",
  "categoria" : "Impostos",
  "descricao" : "Impostos estaduais",
  "valor" : 0.0,
  "problemaDetectado" : null,
  "especialidadeNecessaria" : null,
  "inspetor" : null,
  "avaliacao" : 0.0,
  "pago" : false,
  "formaPagamento" : null,
  "id" : null
}, {
  "numeroOrdem" : "5e5217ab",
  "cliente" : null,
  "veiculo" : null,
  "servicos" : [ ],
  "responsavel" : null,
  "data" : "31/05/2024",
  "horario" : "14:34",
  "status" : "Pendente",
  "elevadorAlocado" : null,
  "itensUtilizados" : [ ],
  "tipo" : "Saída",
  "categoria" : "Impostos",
  "descricao" : "Impostos federais",
  "valor" : 0.0,
  "problemaDetectado" : null,
  "especialidadeNecessaria" : null,
  "inspetor" : null,
  "avaliacao" : 0.0,
  "pago" : false,
  "formaPagamento" : null,
  "id" : null
}, {
  "numeroOrdem" : "091c9a90",
  "cliente" : null,
  "veiculo" : null,
  "servicos" : [ ],
  "responsavel" : null,
  "data" : "05/05/2024",
  "horario" : "14:34",
  "status" : "Pendente",
  "elevadorAlocado" : null,
  "itensUtilizados" : [ ],
  "tipo" : "Entrada",
  "categoria" : "Multas e Taxas",
  "descricao" : "Taxa de atraso - Cliente",
  "valor" : 0.0,
  "problemaDetectado" : null,
  "especialidadeNecessaria" : null,
  "inspetor" : null,
  "avaliacao" : 0.0,
  "pago" : false,
  "formaPagamento" : null,
  "id" : null
}, {
  "numeroOrdem" : "d1e3cfcd",
  "cliente" : null,
  "veiculo" : null,
  "servicos" : [ ],
  "responsavel" : null,
  "data" : "19/05/2024",
  "horario" : "14:34",
  "status" : "Pendente",
  "elevadorAlocado" : null,
  "itensUtilizados" : [ ],
  "tipo" : "Entrada",
  "categoria" : "Multas e Taxas",
  "descricao" : "Taxa de cancelamento - Cliente",
  "valor" : 0.0,
  "problemaDetectado" : null,
  "especialidadeNecessaria" : null,
  "inspetor" : null,
  "avaliacao" : 0.0,
  "pago" : false,
  "formaPagamento" : null,
  "id" : null
}, {
  "numeroOrdem" : "602d3a54",
  "cliente" : null,
  "veiculo" : null,
  "servicos" : [ ],
  "responsavel" : null,
  "data" : "15/05/2024",
  "horario" : "14:34",
  "status" : "Pendente",
  "elevadorAlocado" : null,
  "itensUtilizados" : [ ],
  "tipo" : "Saída",
  "categoria" : "Benefícios",
  "descricao" : "Vale refeição - Funcionários",
  "valor" : 0.0,
  "problemaDetectado" : null,
  "especialidadeNecessaria" : null,
  "inspetor" : null,
  "avaliacao" : 0.0,
  "pago" : false,
  "formaPagamento" : null,
  "id" : null
}, {
  "numeroOrdem" : "93600e33",
  "cliente" : null,
  "veiculo" : null,
  "servicos" : [ ],
  "responsavel" : null,
  "data" : "15/05/2024",
  "horario" : "14:34",
  "status" : "Pendente",
  "elevadorAlocado" : null,
  "itensUtilizados" : [ ],
  "tipo" : "Saída",
  "categoria" : "Benefícios",
  "descricao" : "Vale transporte - Funcionários",
  "valor" : 0.0,
  "problemaDetectado" : null,
  "especialidadeNecessaria" : null,
  "inspetor" : null,
  "avaliacao" : 0.0,
  "pago" : false,
  "formaPagamento" : null,
  "id" : null
}, {
  "numeroOrdem" : "a984fb8e",
  "cliente" : null,
  "veiculo" : null,
  "servicos" : [ ],
  "responsavel" : null,
  "data" : "20/05/2024",
  "horario" : "14:34",
  "status" : "Pendente",
  "elevadorAlocado" : null,
  "itensUtilizados" : [ ],
  "tipo" : "Saída",
  "categoria" : "Benefícios",
  "descricao" : "Plano de saúde - Funcionários",
  "valor" : 0.0,
  "problemaDetectado" : null,
  "especialidadeNecessaria" : null,
  "inspetor" : null,
  "avaliacao" : 0.0,
  "pago" : false,
  "formaPagamento" : null,
  "id" : null
}, {
  "numeroOrdem" : "5508c0a9",
  "cliente" : null,
  "veiculo" : null,
  "servicos" : [ ],
  "responsavel" : null,
  "data" : "04/05/2024",
  "horario" : "14:34",
  "status" : "Pendente",
  "elevadorAlocado" : null,
  "itensUtilizados" : [ ],
  "tipo" : "Entrada",
  "categoria" : "Serviços Emergenciais",
  "descricao" : "Atendimento emergencial - Final de semana",
  "valor" : 0.0,
  "problemaDetectado" : null,
  "especialidadeNecessaria" : null,
  "inspetor" : null,
  "avaliacao" : 0.0,
  "pago" : false,
  "formaPagamento" : null,
  "id" : null
}, {
  "numeroOrdem" : "3c362d29",
  "cliente" : null,
  "veiculo" : null,
  "servicos" : [ ],
  "responsavel" : null,
  "data" : "12/05/2024",
  "horario" : "14:34",
  "status" : "Pendente",
  "elevadorAlocado" : null,
  "itensUtilizados" : [ ],
  "tipo" : "Entrada",
  "categoria" : "Serviços Emergenciais",
  "descricao" : "Atendimento emergencial - Feriado",
  "valor" : 0.0,
  "problemaDetectado" : null,
  "especialidadeNecessaria" : null,
  "inspetor" : null,
  "avaliacao" : 0.0,
  "pago" : false,
  "formaPagamento" : null,
  "id" : null
}, {
  "numeroOrdem" : "5a9a185e",
  "cliente" : null,
  "veiculo" : null,
  "servicos" : [ ],
  "responsavel" : null,
  "data" : "31/05/2024",
  "horario" : "14:34",
  "status" : "Pendente",
  "elevadorAlocado" : null,
  "itensUtilizados" : [ ],
  "tipo" : "Saída",
  "categoria" : "Horas Extras",
  "descricao" : "Pagamento de horas extras",
  "valor" : 0.0,
  "problemaDetectado" : null,
  "especialidadeNecessaria" : null,
  "inspetor" : null,
  "avaliacao" : 0.0,
  "pago" : false,
  "formaPagamento" : null,
  "id" : null
}, {
  "numeroOrdem" : "bf5d94b9",
  "cliente" : null,
  "veiculo" : null,
  "servicos" : [ ],
  "responsavel" : null,
  "data" : "08/05/2024",
  "horario" : "14:34",
  "status" : "Pendente",
  "elevadorAlocado" : null,
  "itensUtilizados" : [ ],
  "tipo" : "Entrada",
  "categoria" : "Garantias",
  "descricao" : "Garantia estendida - Motor",
  "valor" : 0.0,
  "problemaDetectado" : null,
  "especialidadeNecessaria" : null,
  "inspetor" : null,
  "avaliacao" : 0.0,
  "pago" : false,
  "formaPagamento" : null,
  "id" : null
}, {
  "numeroOrdem" : "0985356b",
  "cliente" : null,
  "veiculo" : null,
  "servicos" : [ ],
  "responsavel" : null,
  "data" : "23/05/2024",
  "horario" : "14:34",
  "status" : "Pendente",
  "elevadorAlocado" : null,
  "itensUtilizados" : [ ],
  "tipo" : "Entrada",
  "categoria" : "Garantias",
  "descricao" : "Garantia estendida - Transmissão",
  "valor" : 0.0,
  "problemaDetectado" : null,
  "especialidadeNecessaria" : null,
  "inspetor" : null,
  "avaliacao" : 0.0,
  "pago" : false,
  "formaPagamento" : null,
  "id" : null
}, {
  "numeroOrdem" : "5b3e44e1",
  "cliente" : null,
  "veiculo" : null,
  "servicos" : [ ],
  "responsavel" : null,
  "data" : "26/05/2024",
  "horario" : "14:34",
  "status" : "Pendente",
  "elevadorAlocado" : null,
  "itensUtilizados" : [ ],
  "tipo" : "Saída",
  "categoria" : "Garantias",
  "descricao" : "Honorários de garantia",
  "valor" : 0.0,
  "problemaDetectado" : null,
  "especialidadeNecessaria" : null,
  "inspetor" : null,
  "avaliacao" : 0.0,
  "pago" : false,
  "formaPagamento" : null,
  "id" : null
}, {
  "numeroOrdem" : "e9badd47",
  "cliente" : null,
  "veiculo" : null,
  "servicos" : [ ],
  "responsavel" : null,
  "data" : "06/05/2024",
  "horario" : "14:34",
  "status" : "Pendente",
  "elevadorAlocado" : null,
  "itensUtilizados" : [ ],
  "tipo" : "Entrada",
  "categoria" : "Serviços de Terceiros",
  "descricao" : "Comissão - Guincho",
  "valor" : 0.0,
  "problemaDetectado" : null,
  "especialidadeNecessaria" : null,
  "inspetor" : null,
  "avaliacao" : 0.0,
  "pago" : false,
  "formaPagamento" : null,
  "id" : null
}, {
  "numeroOrdem" : "3ffb3398",
  "cliente" : null,
  "veiculo" : null,
  "servicos" : [ ],
  "responsavel" : null,
  "data" : "17/05/2024",
  "horario" : "14:34",
  "status" : "Pendente",
  "elevadorAlocado" : null,
  "itensUtilizados" : [ ],
  "tipo" : "Entrada",
  "categoria" : "Serviços de Terceiros",
  "descricao" : "Comissão - Lava Jato",
  "valor" : 0.0,
  "problemaDetectado" : null,
  "especialidadeNecessaria" : null,
  "inspetor" : null,
  "avaliacao" : 0.0,
  "pago" : false,
  "formaPagamento" : null,
  "id" : null
}, {
  "numeroOrdem" : "6e38ef4e",
  "cliente" : null,
  "veiculo" : null,
  "servicos" : [ ],
  "responsavel" : null,
  "data" : "10/05/2024",
  "horario" : "14:34",
  "status" : "Pendente",
  "elevadorAlocado" : null,
  "itensUtilizados" : [ ],
  "tipo" : "Saída",
  "categoria" : "Serviços de Terceiros",
  "descricao" : "Serviço de contabilidade",
  "valor" : 0.0,
  "problemaDetectado" : null,
  "especialidadeNecessaria" : null,
  "inspetor" : null,
  "avaliacao" : 0.0,
  "pago" : false,
  "formaPagamento" : null,
  "id" : null
}, {
  "numeroOrdem" : "b7dba27f",
  "cliente" : null,
  "veiculo" : null,
  "servicos" : [ ],
  "responsavel" : null,
  "data" : "25/05/2024",
  "horario" : "14:34",
  "status" : "Pendente",
  "elevadorAlocado" : null,
  "itensUtilizados" : [ ],
  "tipo" : "Saída",
  "categoria" : "Serviços de Terceiros",
  "descricao" : "Serviço de advocacia",
  "valor" : 0.0,
  "problemaDetectado" : null,
  "especialidadeNecessaria" : null,
  "inspetor" : null,
  "avaliacao" : 0.0,
  "pago" : false,
  "formaPagamento" : null,
  "id" : null
}, {
  "numeroOrdem" : "9665e541",
  "cliente" : null,
  "veiculo" : null,
  "servicos" : [ ],
  "responsavel" : null,
  "data" : "20/05/2024",
  "horario" : "14:34",
  "status" : "Pendente",
  "elevadorAlocado" : null,
  "itensUtilizados" : [ ],
  "tipo" : "Entrada",
  "categoria" : "Eventos",
  "descricao" : "Evento - Dia da Mecânica",
  "valor" : 0.0,
  "problemaDetectado" : null,
  "especialidadeNecessaria" : null,
  "inspetor" : null,
  "avaliacao" : 0.0,
  "pago" : false,
  "formaPagamento" : null,
  "id" : null
}, {
  "numeroOrdem" : "8be2a133",
  "cliente" : null,
  "veiculo" : null,
  "servicos" : [ ],
  "responsavel" : null,
  "data" : "20/05/2024",
  "horario" : "14:34",
  "status" : "Pendente",
  "elevadorAlocado" : null,
  "itensUtilizados" : [ ],
  "tipo" : "Saída",
  "categoria" : "Eventos",
  "descricao" : "Organização - Dia da Mecânica",
  "valor" : 0.0,
  "problemaDetectado" : null,
  "especialidadeNecessaria" : null,
  "inspetor" : null,
  "avaliacao" : 0.0,
  "pago" : false,
  "formaPagamento" : null,
  "id" : null
}, {
  "numeroOrdem" : "6870371a",
  "cliente" : null,
  "veiculo" : null,
  "servicos" : [ ],
  "responsavel" : null,
  "data" : "01/05/2024",
  "horario" : "14:34",
  "status" : "Pendente",
  "elevadorAlocado" : null,
  "itensUtilizados" : [ ],
  "tipo" : "Entrada",
  "categoria" : "Assinaturas",
  "descricao" : "Assinatura - Plano de manutenção",
  "valor" : 0.0,
  "problemaDetectado" : null,
  "especialidadeNecessaria" : null,
  "inspetor" : null,
  "avaliacao" : 0.0,
  "pago" : false,
  "formaPagamento" : null,
  "id" : null
}, {
  "numeroOrdem" : "8259b641",
  "cliente" : null,
  "veiculo" : null,
  "servicos" : [ ],
  "responsavel" : null,
  "data" : "15/05/2024",
  "horario" : "14:34",
  "status" : "Pendente",
  "elevadorAlocado" : null,
  "itensUtilizados" : [ ],
  "tipo" : "Entrada",
  "categoria" : "Assinaturas",
  "descricao" : "Assinatura - Plano de manutenção",
  "valor" : 0.0,
  "problemaDetectado" : null,
  "especialidadeNecessaria" : null,
  "inspetor" : null,
  "avaliacao" : 0.0,
  "pago" : false,
  "formaPagamento" : null,
  "id" : null
}, {
  "numeroOrdem" : "a87bc627",
  "cliente" : null,
  "veiculo" : null,
  "servicos" : [ ],
  "responsavel" : null,
  "data" : "01/05/2024",
  "horario" : "14:34",
  "status" : "Pendente",
  "elevadorAlocado" : null,
  "itensUtilizados" : [ ],
  "tipo" : "Saída",
  "categoria" : "Assinaturas",
  "descricao" : "Assinatura - Software de gestão",
  "valor" : 0.0,
  "problemaDetectado" : null,
  "especialidadeNecessaria" : null,
  "inspetor" : null,
  "avaliacao" : 0.0,
  "pago" : false,
  "formaPagamento" : null,
  "id" : null
}, {
  "numeroOrdem" : "17b97cac",
  "cliente" : null,
  "veiculo" : null,
  "servicos" : [ ],
  "responsavel" : null,
  "data" : "15/05/2024",
  "horario" : "14:34",
  "status" : "Pendente",
  "elevadorAlocado" : null,
  "itensUtilizados" : [ ],
  "tipo" : "Saída",
  "categoria" : "Assinaturas",
  "descricao" : "Assinatura - Revistas técnicas",
  "valor" : 0.0,
  "problemaDetectado" : null,
  "especialidadeNecessaria" : null,
  "inspetor" : null,
  "avaliacao" : 0.0,
  "pago" : false,
  "formaPagamento" : null,
  "id" : null
} ]